picklejuice/__init__.py
picklejuice/main.py
Picklejuice-0.0.1.dist-info/METADATA
Picklejuice-0.0.1.dist-info/WHEEL
Picklejuice-0.0.1.dist-info/entry_points.txt
Picklejuice-0.0.1.dist-info/top_level.txt
Picklejuice-0.0.1.dist-info/RECORD
