Metadata-Version: 2.1
Name: Picklejuice
Version: 0.0.1
Summary: Cli tool for quickly translating JSON and YAML config files to Pkl.
Home-page: https://github.com/KDreynolds/vinegar
Author: Kyle Reynolds
Author-email: kylereynoldsdev@gmail.com
Requires-Dist: PyYAML
Requires-Dist: argparse
